threemystic_common/__main__.py
threemystic_common/__version__.py
threemystic_common/common.py
threemystic_common/base_class/base.py
threemystic_common/base_class/base_common.py
threemystic_common/base_class/base_general.py
threemystic_common/base_class/base_provider.py
threemystic_common/base_class/base_script_options.py
threemystic_common/base_class/generate_data/generate_data_handlers.py
threemystic_common/base_class/generate_data/handlers/base.py
threemystic_common/cli/__init__.py
threemystic_common/domain/app_monitoring/common.py
threemystic_common/domain/app_monitoring/performance.py
threemystic_common/domain/cmdb/aws.py
threemystic_common/domain/cmdb/azure.py
threemystic_common/domain/cmdb/common.py
threemystic_common/domain/cmdb/base_class/base.py
threemystic_common/domain/encryption/common.py
threemystic_common/domain/encryption/hash.py
threemystic_common/domain/exception/argument.py
threemystic_common/domain/exception/common.py
threemystic_common/domain/exception/function.py
threemystic_common/domain/exception/generic.py
threemystic_common/domain/exception/base_class/base.py
threemystic_common/domain/generate_data/generate.py
threemystic_common/domain/graph/common.py
threemystic_common/domain/graph/msgraph.py
threemystic_common/domain/graph/base_class/base.py
threemystic_common/domain/graph/config/msgraph.py
threemystic_common/domain/hashicorp/common.py
threemystic_common/domain/hashicorp/vault.py
threemystic_common/domain/helpers/app.py
threemystic_common/domain/helpers/config.py
threemystic_common/domain/helpers/currency.py
threemystic_common/domain/helpers/json.py
threemystic_common/domain/helpers/parallel_processing.py
threemystic_common/domain/helpers/path.py
threemystic_common/domain/helpers/yaml.py
threemystic_common/domain/helpers/type/bool.py
threemystic_common/domain/helpers/type/common.py
threemystic_common/domain/helpers/type/datetime.py
threemystic_common/domain/helpers/type/dictionary.py
threemystic_common/domain/helpers/type/general.py
threemystic_common-0.1.17.dist-info/METADATA
threemystic_common-0.1.17.dist-info/WHEEL
threemystic_common-0.1.17.dist-info/licenses/LICENSE
threemystic_common-0.1.17.dist-info/RECORD
