Metadata-Version: 2.1
Name: threemystic-common
Version: 0.1.17
Summary: Common Library for for various tool sets
Project-URL: Homepage, https://github.com/3MysticApes/3mystic_common
Project-URL: Bug Tracker, https://github.com/3MysticApes/3mystic_common/issues
Author: Ron Truex
License-Expression: MIT
License-File: LICENSE
Classifier: License :: OSI Approved :: MIT License
Classifier: Natural Language :: English
Classifier: Operating System :: OS Independent
Classifier: Programming Language :: Python :: 3.8
Classifier: Programming Language :: Python :: 3.9
Classifier: Programming Language :: Python :: 3.10
Classifier: Programming Language :: Python :: 3.11
Classifier: Programming Language :: Python :: Implementation :: CPython
Classifier: Programming Language :: Python :: Implementation :: PyPy
Requires-Python: >=3.8
Requires-Dist: asyncio>=3.4.3
Requires-Dist: colorama; platform_system == 'Windows'
Requires-Dist: cryptography>=38.0.3
Requires-Dist: currencyconverter>=0.17
Requires-Dist: openpyxl>=3.0.9
Requires-Dist: pathvalidate>=3.0.0
Requires-Dist: pycryptodomex>=3.14.1
Requires-Dist: python-dateutil>=2.8.2
Requires-Dist: requests>=2.27.1
Requires-Dist: ruamel-yaml>=0.17.31
Requires-Dist: typing-extensions>=4.4.0
